zoidberg/__init__.py
zoidberg/_version.py
zoidberg/boundary.py
zoidberg/diff.py
zoidberg/field.py
zoidberg/fieldtracer.py
zoidberg/grid.py
zoidberg/plot.py
zoidberg/poloidal_grid.py
zoidberg/progress.py
zoidberg/rzline.py
zoidberg/smooth.py
zoidberg/spectralline.py
zoidberg/stencil_dagp_fv.py
zoidberg/test_diff.py
zoidberg/test_field.py
zoidberg/test_fieldtracer.py
zoidberg/test_grid.py
zoidberg/test_poloidal_grid.py
zoidberg/test_rzline.py
zoidberg/test_smooth.py
zoidberg/test_zoidberg.py
zoidberg/zoidberg.py
zoidberg/examples/common.py
zoidberg/examples/rotating_ellipse.py
zoidberg/examples/screwpinch.py
zoidberg-0.2.3.dist-info/licenses/LICENSE
zoidberg-0.2.3.dist-info/METADATA
zoidberg-0.2.3.dist-info/WHEEL
zoidberg-0.2.3.dist-info/entry_points.txt
zoidberg-0.2.3.dist-info/top_level.txt
zoidberg-0.2.3.dist-info/RECORD
